Turing_Pattern_Simulator/__init__.py
Turing_Pattern_Simulator/main.py
Turing_pattern_simulator-1.dist-info/METADATA
Turing_pattern_simulator-1.dist-info/WHEEL
Turing_pattern_simulator-1.dist-info/top_level.txt
Turing_pattern_simulator-1.dist-info/RECORD
